MANIFEST.in
README.txt
setup.cfg
setup.py
mwlib/__init__.py
mwlib.zim.egg-info/PKG-INFO
mwlib.zim.egg-info/SOURCES.txt
mwlib.zim.egg-info/dependency_links.txt
mwlib.zim.egg-info/entry_points.txt
mwlib.zim.egg-info/namespace_packages.txt
mwlib.zim.egg-info/not-zip-safe
mwlib.zim.egg-info/requires.txt
mwlib.zim.egg-info/top_level.txt
mwlib/zim/__init__.py
mwlib/zim/collection.py
mwlib/zim/config.py
mwlib/zim/favicon.png
mwlib/zim/siteconfig.py
mwlib/zim/wp.css
mwlib/zim/zimwriter.py