Metadata-Version: 1.0
Name: mwlib.zim
Version: 0.3.0
Summary: generate zim files from mediawiki markup
Home-page: http://code.pediapress.com/
Author: pediapress.com
Author-email: info@pediapress.com
License: BSD License
Platform: UNKNOWN
